ACKNOWLEDGEMENTS.md
CHANGELOG.md
LICENSE
MANIFEST.in
README.rst
setup.cfg
setup.py
test_isort.py
isort/__init__.py
isort/__main__.py
isort/finders.py
isort/hooks.py
isort/isort.py
isort/main.py
isort/natural.py
isort/pie_slice.py
isort/pylama_isort.py
isort/settings.py
isort/utils.py
isort_plus.egg-info/PKG-INFO
isort_plus.egg-info/SOURCES.txt
isort_plus.egg-info/dependency_links.txt
isort_plus.egg-info/entry_points.txt
isort_plus.egg-info/requires.txt
isort_plus.egg-info/top_level.txt